hackPyrateBus/AT24CXXX.py
hackPyrateBus/__init__.py
vendor/__init__.py
vendor/pyBusPirateLite/BitBang.py
vendor/pyBusPirateLite/I2C.py
vendor/pyBusPirateLite/I2Chigh.py
vendor/pyBusPirateLite/SPI.py
vendor/pyBusPirateLite/UART.py
vendor/pyBusPirateLite/UC.py
vendor/pyBusPirateLite/__init__.py
vendor/pyBusPirateLite/base.py
vendor/pyBusPirateLite/common_functions.py
vendor/pyBusPirateLite/onewire.py
vendor/pyBusPirateLite/rawwire.py
hackPyrateBus-0.0.6.dist-info/LICENSE
hackPyrateBus-0.0.6.dist-info/METADATA
hackPyrateBus-0.0.6.dist-info/WHEEL
hackPyrateBus-0.0.6.dist-info/top_level.txt
hackPyrateBus-0.0.6.dist-info/RECORD
