Metadata-Version: 2.1
Name: hackPyrateBus
Version: 0.0.6
Summary: Python library with high-level functions to interact with specific ICs using Bus Pirate
Home-page: https://github.com/julianvilas/hackPyrateBus
License: GPLv3
Keywords: BusPirate
Classifier: Development Status :: 3 - Alpha
Classifier: License :: OSI Approved :: GNU General Public License v3 (GPLv3)
Classifier: Programming Language :: Python :: 3.12
Classifier: Topic :: Software Development :: Libraries :: Python Modules
Requires-Python: >=3.11
License-File: LICENSE
Requires-Dist: pyserial
